tree_sitter_rttm/__init__.pyi
tree_sitter_rttm/binding.c
tree_sitter_rttm/__init__.py
tree_sitter_rttm/py.typed
tree_sitter_rttm/_binding.abi3.so
tree_sitter_rttm/queries/highlights.scm
tree_sitter_rttm-0.1.1.dist-info/RECORD
tree_sitter_rttm-0.1.1.dist-info/WHEEL
tree_sitter_rttm-0.1.1.dist-info/top_level.txt
tree_sitter_rttm-0.1.1.dist-info/METADATA
tree_sitter_rttm-0.1.1.dist-info/licenses/LICENSE
