Metadata-Version: 2.4
Name: tree-sitter-rttm
Version: 0.1.1
Summary: A Tree-sitter grammar for RTTM files
Author-email: Maksim Panfilov <maks@panf.me>
License: MIT
Project-URL: Homepage, https://github.com/mxpanf/tree-sitter-rttm
Project-URL: Funding, https://github.com/sponsors/mxpanf
Keywords: incremental,parsing,tree-sitter,rttm
Classifier: Intended Audience :: Developers
Classifier: Topic :: Software Development :: Compilers
Classifier: Topic :: Text Processing :: Linguistic
Classifier: Typing :: Typed
Requires-Python: >=3.10
License-File: LICENSE
Provides-Extra: core
Requires-Dist: tree-sitter~=0.24; extra == "core"
Dynamic: license-file
